slack_wlan_status_updater/__init__.py
slack_wlan_status_updater/__main__.py
slack_wlan_status_updater/status_selector.py
slack_wlan_status_updater/status_setter.py
slack_wlan_status_updater-0.1.1.dist-info/entry_points.txt
slack_wlan_status_updater-0.1.1.dist-info/WHEEL
slack_wlan_status_updater-0.1.1.dist-info/METADATA
slack_wlan_status_updater-0.1.1.dist-info/RECORD
