Metadata-Version: 2.1
Name: slack-wlan-status-updater
Version: 0.1.1
Summary: Update Slack status based on WLAN network
License: MIT
Author: Martin Ueding
Author-email: mu@martin-ueding.de
Requires-Python: >=3.11,<4.0
Classifier: License :: OSI Approved :: MIT License
Classifier: Programming Language :: Python :: 3
